LICENSE
MANIFEST.in
README.rst
setup.py
jingtai/.DS_Store
jingtai/__init__.py
jingtai/assets.py
jingtai/compat.py
jingtai/reload.js
jingtai/server.py
jingtai/site.py
jingtai/watcher.py
jingtai.egg-info/PKG-INFO
jingtai.egg-info/SOURCES.txt
jingtai.egg-info/dependency_links.txt
jingtai.egg-info/entry_points.txt
jingtai.egg-info/not-zip-safe
jingtai.egg-info/requires.txt
jingtai.egg-info/top_level.txt
jingtai/command/__init__.py
jingtai/command/resources/404.html
jingtai/command/resources/base.plim
jingtai/command/resources/index.plim
jingtai/command/resources/tasks.py
jingtai/transformers/__init__.py
jingtai/transformers/base.py
jingtai/transformers/coffeescript.py
jingtai/transformers/md.py
jingtai/transformers/page.py
jingtai/transformers/plimtemplate.py
jingtai/transformers/rapydscript.py
jingtai/transformers/rst.py
jingtai/transformers/stylus.py
jingtai/transformers/util.py